Metadata-Version: 1.0
Name: sms
Version: 0.2
Summary: SMS sending and receiving with enfora gsm modems
Home-page: http://pypi.python.org/pypi/sms
Author: Amos Latteier
Author-email: amos@latteier.com
License: MIT
Platform: UNKNOWN
Classifier: License :: OSI Approved :: MIT License
Classifier: Operating System :: MacOS
Classifier: Operating System :: Microsoft :: Windows
Classifier: Operating System :: POSIX
Classifier: Topic :: Communications :: Telephony
